academic_publication_manager/BaseBodyUi.py
academic_publication_manager/BaseContextMenu.py
academic_publication_manager/BaseMenuBar.py
academic_publication_manager/BaseToolBar.py
academic_publication_manager/__init__.py
academic_publication_manager/about.py
academic_publication_manager/desktop.py
academic_publication_manager/program.py
academic_publication_manager/icons/logo.png
academic_publication_manager/modules/__init__.py
academic_publication_manager/modules/customtreeview.py
academic_publication_manager/modules/production.py
academic_publication_manager/modules/to_bibtex.py
academic_publication_manager/modules/wabout.py
academic_publication_manager-0.1.3.dist-info/licenses/LICENSE
academic_publication_manager-0.1.3.dist-info/METADATA
academic_publication_manager-0.1.3.dist-info/WHEEL
academic_publication_manager-0.1.3.dist-info/entry_points.txt
academic_publication_manager-0.1.3.dist-info/top_level.txt
academic_publication_manager-0.1.3.dist-info/RECORD
