Metadata-Version: 2.4
Name: academic_publication_manager
Version: 0.1.3
Summary: Simple academic publication manager GUI.
Author-email: Fernando Pujaico Rivera <fernando.pujaico.rivera@gmail.com>
Maintainer-email: Fernando Pujaico Rivera <fernando.pujaico.rivera@gmail.com>
License-Expression: GPL-3.0-only WITH Classpath-exception-2.0 OR BSD-3-Clause
Project-URL: Bug Reports, https://github.com/trucomanx/AcademicPublicationManager/issues
Project-URL: Funding, https://trucomanx.github.io/en/funding.html
Project-URL: Documentation, https://github.com/trucomanx/AcademicPublicationManager/tree/main/doc
Project-URL: Source, https://github.com/trucomanx/AcademicPublicationManager
Keywords: writing,research
Classifier: Programming Language :: Python :: 3
Classifier: Operating System :: OS Independent
Requires-Python: >=3.8
License-File: LICENSE
Requires-Dist: PyQt5
Requires-Dist: bibtexparser
Dynamic: license-file
